CONTRIBUTORS
LICENSE
README.md
ruvpy/__init__.py
ruvpy/damage_functions.py
ruvpy/data_classes.py
ruvpy/decision_rules.py
ruvpy/economic_models.py
ruvpy/helpers.py
ruvpy/multi_timestep.py
ruvpy/relative_utility_value.py
ruvpy/single_timestep.py
ruvpy/utility_functions.py
ruvpy-1.0.1.dist-info/LICENSE
ruvpy-1.0.1.dist-info/METADATA
ruvpy-1.0.1.dist-info/NOTICE
ruvpy-1.0.1.dist-info/WHEEL
ruvpy-1.0.1.dist-info/RECORD
