Metadata-Version: 2.1
Name: ruvpy
Version: 1.0.1
Summary: Reference implementation of Relative Utility Value (RUV) to quantify forecast value
License: Apache-2.0
Author: Richard Laugesen
Author-email: richard@laugesen.com.au
Requires-Python: >=3.10
Classifier: Development Status :: 5 - Production/Stable
Classifier: Intended Audience :: Science/Research
Classifier: License :: OSI Approved :: Apache Software License
Classifier: Operating System :: OS Independent
Classifier: Programming Language :: Python :: 3
Classifier: Programming Language :: Python :: 3.10
Classifier: Programming Language :: Python :: 3.11
Classifier: Programming Language :: Python :: 3.12
Classifier: Topic :: Office/Business :: Financial
Classifier: Topic :: Scientific/Engineering
Classifier: Topic :: Scientific/Engineering :: Artificial Intelligence
Classifier: Topic :: Scientific/Engineering :: Atmospheric Science
Classifier: Topic :: Scientific/Engineering :: Hydrology
Classifier: Topic :: Scientific/Engineering :: Information Analysis
Classifier: Topic :: Scientific/Engineering :: Mathematics
Provides-Extra: examples
Requires-Dist: numpy (>=1.24.4)
Requires-Dist: pathos (>=0.3.0)
Requires-Dist: scipy (>=1.9.3)
Project-URL: Citation, https://doi.org/10.5281/zenodo.13939198
Project-URL: Documentation, https://github.com/richardlaugesen/ruvpy#readme
Project-URL: Homepage, https://github.com/richardlaugesen/ruvpy
Project-URL: Issue Tracker, https://github.com/richardlaugesen/ruvpy/issues
Project-URL: Source Code, https://github.com/richardlaugesen/ruvpy
